LICENSE.txt
MANIFEST.in
README.md
requirements.txt
requirements_dev.txt
setup.cfg
setup.py
tox-integration.ini
tox.ini
integration_tests/test_gsheets_integration.py
pygsheetsorm/__init__.py
pygsheetsorm/pygsheetsorm.py
pygsheetsorm.egg-info/PKG-INFO
pygsheetsorm.egg-info/SOURCES.txt
pygsheetsorm.egg-info/dependency_links.txt
pygsheetsorm.egg-info/not-zip-safe
pygsheetsorm.egg-info/requires.txt
pygsheetsorm.egg-info/top_level.txt
tests/test_pygsheetsorm.py
tests/test_type_conversion.py