Metadata-Version: 1.1
Name: pygsheetsorm
Version: 1.0.1
Summary: Easy to use library to map a Google Sheet Worksheet to a Python object.
Home-page: https://github.com/salesforce/pygsheetsorm
Author: Nelson Wolf
Author-email: nelson.wolf@salesforce.com
License: BSD 3-clause
Platform: UNKNOWN
Classifier: Development Status :: 2 - Pre-Alpha
Classifier: Intended Audience :: Developers
Classifier: License :: OSI Approved :: BSD License
Classifier: Natural Language :: English
Classifier: Programming Language :: Python :: 2
Classifier: Programming Language :: Python :: 2.7
Classifier: Programming Language :: Python :: 3
Classifier: Programming Language :: Python :: 3.6
